openblock_api_sdk_python/__init__.py
openblock_api_sdk_python/client.py
openblock_api_sdk_python/param/company_param.py
openblock_api_sdk_python-0.0.1.dist-info/METADATA
openblock_api_sdk_python-0.0.1.dist-info/WHEEL
openblock_api_sdk_python-0.0.1.dist-info/RECORD
