Metadata-Version: 2.1
Name: openblock-api-sdk-python
Version: 0.0.1
Summary: 
Author: wangzhipeng
Author-email: 17826800084g@gmail.com
Requires-Python: >=3.8.10,<4.0.0
Classifier: Programming Language :: Python :: 3
Classifier: Programming Language :: Python :: 3.9
Classifier: Programming Language :: Python :: 3.10
Classifier: Programming Language :: Python :: 3.11
Classifier: Programming Language :: Python :: 3.12
Requires-Dist: requests (>=2.31.0,<3.0.0)
